static_graphviz/__init__.py
static_graphviz/_add_paths.py
static_graphviz/cli.py
static_graphviz/run.py
static_graphviz-1.14.dist-info/licenses/LICENSE
static_graphviz-1.14.dist-info/METADATA
static_graphviz-1.14.dist-info/WHEEL
static_graphviz-1.14.dist-info/entry_points.txt
static_graphviz-1.14.dist-info/top_level.txt
static_graphviz-1.14.dist-info/RECORD
