Metadata-Version: 2.4
Name: static-graphviz
Version: 1.14
Summary: Cross platform ffmpeg to work on various systems.
Home-page: https://github.com/zackees/static-graphviz
Author-email: Zach Vorhies <dont@email.me>
Maintainer: Zachary Vorhies
License: MIT
Requires-Python: >=3.10.0
License-File: LICENSE
Requires-Dist: requests
Requires-Dist: filelock
Requires-Dist: progress
Dynamic: home-page
Dynamic: license-file
Dynamic: maintainer
